osintbuddy/__init__.py
osintbuddy/ascii.py
osintbuddy/errors.py
osintbuddy/ob.py
osintbuddy/plugins.py
osintbuddy/server.py
osintbuddy/elements/__init__.py
osintbuddy/elements/base.py
osintbuddy/elements/displays.py
osintbuddy/elements/inputs.py
osintbuddy/templates/__init__.py
osintbuddy/templates/default.py
osintbuddy/utils/__init__.py
osintbuddy/utils/generic.py
osintbuddy-0.0.4rc51.post1.dist-info/entry_points.txt
osintbuddy-0.0.4rc51.post1.dist-info/LICENSE
osintbuddy-0.0.4rc51.post1.dist-info/WHEEL
osintbuddy-0.0.4rc51.post1.dist-info/METADATA
osintbuddy-0.0.4rc51.post1.dist-info/RECORD
