Metadata-Version: 2.1
Name: osintbuddy
Version: 0.0.4rc51.post1
Summary: OSINTBuddy - mine, merge, and map data for novel insights
Author-email: jerlendds <support@forum.osintbuddy.com>
Requires-Python: >=3.11
Classifier: Development Status :: 3 - Alpha
Classifier: Intended Audience :: Developers
Classifier: License :: OSI Approved :: GNU Affero General Public License v3
Classifier: Programming Language :: Python :: 3.11
Requires-Dist: selenium>=4.9.0
Requires-Dist: sqlalchemy-json==0.7.0
Requires-Dist: SQLAlchemy-Utils==0.41.1
Requires-Dist: playwright>=1.39.0
Requires-Dist: httpx>=0.25.0
Requires-Dist: beautifulsoup4==4.12.2
Requires-Dist: pyfiglet==0.8.post1
Requires-Dist: termcolor==2.3.0
Requires-Dist: fastapi==0.103.2
Requires-Dist: uvicorn==0.22.0
Requires-Dist: uvloop==0.17.0
Requires-Dist: pydantic==2.4.2
Requires-Dist: pydantic-settings==2.0.3
Requires-Dist: yq==3.2.3
Requires-Dist: jedi-language-server==0.41.1
Requires-Dist: websockets==11.0.3
Requires-Dist: astroid==2.15.4 ; extra == "test"
Requires-Dist: colorama==0.4.6 ; extra == "test"
Requires-Dist: dill==0.3.6 ; extra == "test"
Requires-Dist: eradicate==2.2.0 ; extra == "test"
Requires-Dist: exceptiongroup==1.1.1 ; extra == "test"
Requires-Dist: iniconfig==2.0.0 ; extra == "test"
Requires-Dist: isort==5.12.0 ; extra == "test"
Requires-Dist: lazy-object-proxy==1.9.0 ; extra == "test"
Requires-Dist: mando==0.7.1 ; extra == "test"
Requires-Dist: mccabe==0.7.0 ; extra == "test"
Requires-Dist: mypy==1.3.0 ; extra == "test"
Requires-Dist: mypy-extensions==1.0.0 ; extra == "test"
Requires-Dist: packaging==23.1 ; extra == "test"
Requires-Dist: platformdirs==3.5.1 ; extra == "test"
Requires-Dist: pluggy==1.0.0 ; extra == "test"
Requires-Dist: pycodestyle==2.10.0 ; extra == "test"
Requires-Dist: pydocstyle==6.3.0 ; extra == "test"
Requires-Dist: pyflakes==3.0.1 ; extra == "test"
Requires-Dist: pylama==8.4.1 ; extra == "test"
Requires-Dist: pylint==2.17.4 ; extra == "test"
Requires-Dist: pytest==7.3.1 ; extra == "test"
Requires-Dist: radon==6.0.1 ; extra == "test"
Requires-Dist: six==1.16.0 ; extra == "test"
Requires-Dist: snowballstemmer==2.2.0 ; extra == "test"
Requires-Dist: toml==0.10.2 ; extra == "test"
Requires-Dist: tomli==2.0.1 ; extra == "test"
Requires-Dist: tomlkit==0.11.8 ; extra == "test"
Requires-Dist: typing-extensions==4.5.0 ; extra == "test"
Requires-Dist: vulture==2.7 ; extra == "test"
Requires-Dist: wrapt==1.15.0 ; extra == "test"
Project-URL: Documentation, https://docs.osintbuddy.com/
Project-URL: Source, https://github.com/jerlendds/osintbuddy-plugins
Project-URL: Tracker, https://github.com/jerlendds/osintbuddy/issues
Provides-Extra: test
